dockerasmus/__init__.py
dockerasmus/__main__.py
dockerasmus/cli.py
dockerasmus/spatial.py
dockerasmus/constants/__init__.py
dockerasmus/constants/aminoacid_charges.csv
dockerasmus/constants/aminoacid_pwd.csv
dockerasmus/constants/aminoacid_radius.csv
dockerasmus/constants/atomic_masses.csv
dockerasmus/constants/atomic_pwd.csv
dockerasmus/constants/atomic_radius.csv
dockerasmus/pdb/__init__.py
dockerasmus/pdb/atom.py
dockerasmus/pdb/chain.py
dockerasmus/pdb/protein.py
dockerasmus/pdb/residue.py
dockerasmus/score/__init__.py
dockerasmus/score/function.py
dockerasmus/score/components/__init__.py
dockerasmus/score/components/base.py
dockerasmus/score/components/coulomb.py
dockerasmus/score/components/fabiola.py
dockerasmus/score/components/lennard_jones.py
dockerasmus/score/components/screened_coulomb.py
dockerasmus/score/requirements/__init__.py
dockerasmus/score/requirements/base.py
dockerasmus/score/requirements/distance.py
dockerasmus/utils/__init__.py
dockerasmus/utils/decorators.py
dockerasmus/utils/iterators.py
dockerasmus/utils/matrices.py
dockerasmus/utils/tensors.py
dockerasmus-0.1.1.dist-info/DESCRIPTION.rst
dockerasmus-0.1.1.dist-info/METADATA
dockerasmus-0.1.1.dist-info/RECORD
dockerasmus-0.1.1.dist-info/WHEEL
dockerasmus-0.1.1.dist-info/metadata.json
dockerasmus-0.1.1.dist-info/top_level.txt
