Metadata-Version: 2.0
Name: dockerasmus
Version: 0.1.1
Summary: An easy to use docking library.
Home-page: https://gitlab.com/althonos/dockerasmus
Author: Martin Larralde
Author-email: martin.larralde@ens-cachan.fr
License: GPLv3
Keywords: bioinformatics,docking,protein,PDB,structural,biology
Platform: UNKNOWN
Classifier: Development Status :: 3 - Alpha
Classifier: Programming Language :: Python
Classifier: Programming Language :: Python :: 2
Classifier: Programming Language :: Python :: 2.7
Classifier: Programming Language :: Python :: 3
Classifier: Programming Language :: Python :: 3.4
Classifier: Programming Language :: Python :: 3.5
Classifier: Programming Language :: Python :: 3.6
Classifier: Intended Audience :: Developers
Classifier: Intended Audience :: Science/Research
Classifier: License :: OSI Approved :: GNU General Public License v3 (GPLv3)
Classifier: Topic :: Scientific/Engineering :: Bio-Informatics
Classifier: Topic :: Scientific/Engineering :: Chemistry
Classifier: Topic :: Software Development :: Libraries :: Python Modules
Classifier: Operating System :: OS Independent
Requires-Dist: numpy
Requires-Dist: six
Provides-Extra: docs
Requires-Dist: numpy; extra == 'docs'
Requires-Dist: six; extra == 'docs'
Requires-Dist: sphinx; extra == 'docs'
Requires-Dist: sphinxjp.themes.basicstrap; extra == 'docs'
